{
  "dataList": [
    {
      "id": 0,
      "place": "Reconstructing K Corp. Laboratory",
      "content": "1627 7 4888 1 498223 9888 14 462 3257523 4822 14423 462 614492, 7 48693 222 1 970673 84 1 41879713 662 4981775 4388 46273 2522."
    },
    {
      "id": 1,
      "model": "\ub418\uc0b4\uc544\ub09c\ud574\ubc29\uc5f0\ud569",
      "teller": "3257523? 9762314787 19971742 828623",
      "title": "4246789855 9762314787 19971742",
      "content": "676... 16621677..."
    },
    {
      "id": 2,
      "model": "\ud30c\uc6b0\uc2a4\ud2b8",
      "content": "31742, 38 586 4229 462 589327 68656'2 93222742 721365?"
    },
    {
      "id": 3,
      "model": "\ud30c\uc6b0\uc2a4\ud2b8",
      "content": "9124 4782 7 211, 462 589327 68656 112 983523 7748 38756128'2 6835..."
    },
    {
      "id": 4,
      "model": "\ub2e8\ud14c",
      "content": "<I can't find her corpse anywhere... Must have been moved away when the space twisted.>"
    },
    {
      "id": 5,
      "model": "\ub2e8\ud14c",
      "content": "<But it can't be too far away, I'm sure of it. I can feel it...>"
    },
    {
      "id": 6,
      "model": "\uc2f1\ud074\ub808\uc5b4",
      "content": "16, 7 387'4 222 38753175, 274623."
    },
    {
      "id": 7,
      "model": "\ud30c\uc6b0\uc2a4\ud2b8",
      "content": "62'2 978295 48 62 77 462 2182 98414787 12 462 32421223 38756128."
    },
    {
      "id": 8,
      "model": "\uc2f1\ud074\ub808\uc5b4",
      "content": "67479 781... 12'52 23923727423 462 4146882 84 258 14 462 2182 4782. 7 56222 74'2 461782 48 31742'2 9134746913... 14477745, 74 4614 81822 22722...?"
    },
    {
      "id": 9,
      "model": "\ud788\uc2a4\ud074\ub9ac\ud504",
      "content": "462 6299 132 586 4198775 16864. 14477745?"
    },
    {
      "id": 10,
      "model": "\ud30c\uc6b0\uc2a4\ud2b8",
      "content": "38 586 8217 462 461772 6773775 62?"
    },
    {
      "id": 11,
      "model": "\uc2f1\ud074\ub808\uc5b4",
      "content": "5216... 4672 72 872 84 46273 7749627422, 37564?"
    },
    {
      "id": 12,
      "model": "\uc2f1\ud074\ub808\uc5b4",
      "content": "4627, 1614 1799 619927 74 2882872 9782 38753175 5242 48 462 4146882?"
    },
    {
      "id": 13,
      "model": "\ub3c8\ud0a4\ud638\ud14c",
      "content": "4324 784, 483 12 26199 4773 864 4388 781 87!"
    },
    {
      "id": 14,
      "model": "\ub3c8\ud0a4\ud638\ud14c",
      "content": "924 62 51706726 462 4822 16213 483 781!"
    }
  ]
}