{
  "dataList": [
    {
      "id": 0,
      "model": "\ub9c8\uc655\ud788\uc2a4\ud074\ub9ac\ud5041",
      "teller": "6214649744?",
      "title": "???",
      "content": "25235 414623772... 112 32247723... 48 62 872231692."
    },
    {
      "id": 1,
      "model": "\ub9c8\uc655\ud788\uc2a4\ud074\ub9ac\ud5041",
      "teller": "6214649744?",
      "title": "???",
      "content": "6241622 84 6214649744."
    },
    {
      "id": 2,
      "model": "\ub9c8\uc655\ud788\uc2a4\ud074\ub9ac\ud5041",
      "teller": "6214649744?",
      "title": "???",
      "content": "4614 72 165... 7 8624 8799... 25235 6214649744, 77 25235 18393."
    },
    {
      "id": 3,
      "model": "\ub9c8\uc655\ud788\uc2a4\ud074\ub9ac\ud5041",
      "teller": "6214649744?",
      "title": "???",
      "content": "586 18693 6152... 3872 462 2182."
    }
  ]
}