{
  "dataList": [
    {
      "id": "announcer_cheer_3_1",
      "dlg": "461387\u20192 784 5883 14 1174775. 586 524 100 2248732."
    },
    {
      "id": "announcer_cheer_3_2",
      "dlg": "9215775 1746 82967 74 586\u201932 9142."
    },
    {
      "id": "announcer_specialcheer_3_1",
      "dlg": "9122275232 132 6634. 387\u20194 435."
    },
    {
      "id": "announcer_specialcheer_3_2",
      "dlg": "165 373 4625 4637 7748 82967 432142? 461387\u20192 213 781."
    },
    {
      "id": "announcer_enemy_break_3_1",
      "dlg": "4822 132 199 267885-26185. 1 461742, 727\u20194 74?"
    },
    {
      "id": "announcer_ally_break_3_1",
      "dlg": "461387 373 4299 586 48 412427 5863 221462942."
    },
    {
      "id": "announcer_killenemy_3_1",
      "dlg": "82967 613 6227 9248726. 1299 3872, 37564?"
    },
    {
      "id": "announcer_ally_dead_3_1",
      "dlg": "1 912227523 1274 199 6626. 387\u20194 483524 48 4748 5863 4848 91423."
    },
    {
      "id": "announcer_enemy_adv_3_1",
      "dlg": "462 613 5652 132 1777775. 461387 87564 7624 69 173 92152."
    },
    {
      "id": "announcer_ally_adv_3_1",
      "dlg": "188688. 4672 2732\u2014462 1777232\u2019 2732."
    },
    {
      "id": "announcer_danger_3_1",
      "dlg": "\u2026883419 92379? 6227 416564 4672 963122."
    },
    {
      "id": "announcer_enemy_specialskill_3_1",
      "dlg": "462 538673 72 2618775. 461387\u20192 368695-468695 488."
    },
    {
      "id": "announcer_enemy_specialgimmick_3_1",
      "dlg": "1 8524235. 78 4299775 1614 1799 989 69."
    },
    {
      "id": "announcer_advatk_physical_3_1",
      "dlg": "1 912227523 5152 4628 1 68778."
    },
    {
      "id": "announcer_disadvatk_physical_3_1",
      "dlg": "4614 872 373 7846775. 36885."
    },
    {
      "id": "announcer_advatk_attr_3_1",
      "dlg": "4625 2173 8781775 1614 586 373 13875 72 462 47324 2429."
    },
    {
      "id": "announcer_disadvatk_attr_3_1",
      "dlg": "38 586 2527 6152 175 7321 1614 586 373 13875? \u2026921374 4614 4388 1 33181."
    },
    {
      "id": "announcer_enemy_specialbuff_3_1",
      "dlg": "46822 4822 9888 9782 4625\u201932 77 1 5883 8883. 74 692242 461387."
    },
    {
      "id": "announcer_enemy_specialdebuff_3_1",
      "dlg": "9888 14 4628. 4625 11771 4822 4888722."
    },
    {
      "id": "announcer_ally_specialbuff_3_1",
      "dlg": "373 288246775 5883 619927 48 462 9122275232?"
    },
    {
      "id": "announcer_ally_specialdebuff_3_1",
      "dlg": "\u202646232\u20192 1 38555 615 62981 5863 22142. 78 46381775 69 87 82967."
    },
    {
      "id": "announcer_enemy_destroy_3_1",
      "dlg": "81469178. 1 2984 63882. 8229 4831133."
    },
    {
      "id": "announcer_enemy_destroy_3_2",
      "dlg": "9122275232 7624 63882 4614. 78 872 1799 4299 62 48 915 483 462 318152, 28 58 87."
    },
    {
      "id": "announcer_round_takebigdmg_3_1",
      "dlg": "461387\u20192 199 297775."
    },
    {
      "id": "announcer_round_takebigdmg_3_2",
      "dlg": "229, 4614 988823 66345."
    },
    {
      "id": "announcer_round_givebigdmg_3_1",
      "dlg": "1 6652 2644222. 461387\u20192 2347423. 9238722787 48 2775?"
    },
    {
      "id": "announcer_round_givebigdmg_3_2",
      "dlg": "1681! 461387\u20192 2684823 488."
    },
    {
      "id": "announcer_multikillenemy_3_1",
      "dlg": "\u201c418 3142 1746 872 24872\u201d, 37564? 461387 1799 321133 586 1746 9142."
    },
    {
      "id": "announcer_equip_3_1",
      "dlg": "461387 1992132. 199 3278742."
    }
  ]
}